EShAY/EShAY.py
EShAY/__init__.py
eshay-1.0.4.dist-info/licenses/LICENSE
eshay-1.0.4.dist-info/METADATA
eshay-1.0.4.dist-info/WHEEL
eshay-1.0.4.dist-info/top_level.txt
eshay-1.0.4.dist-info/RECORD
