Metadata-Version: 2.4
Name: EShAY
Version: 1.0.4
Summary: A package to look at similarity between two genetic datasets. Useful for finding duplicate tissue donors betwen studies.
Author-email: Dr Gabe O'Reilly <g.oreilly@garvan.org.au>
License-Expression: MIT
Project-URL: Homepage, https://github.com/GabeDO/SimilarityPythonPackage
Classifier: Programming Language :: Python :: 3
Classifier: Operating System :: OS Independent
Requires-Python: >=3
License-File: LICENSE
Dynamic: license-file
